mkpipe_extractor_clickhouse/__init__.py
mkpipe_extractor_clickhouse/jars/com.clickhouse_clickhouse-client-0.8.0.jar
mkpipe_extractor_clickhouse/jars/com.clickhouse_clickhouse-data-0.8.0.jar
mkpipe_extractor_clickhouse/jars/com.clickhouse_clickhouse-http-client-0.8.0.jar
mkpipe_extractor_clickhouse/jars/com.clickhouse_clickhouse-jdbc-0.8.0.jar
mkpipe_extractor_clickhouse/jars/com.clickhouse_client-v2-0.8.0.jar
mkpipe_extractor_clickhouse/jars/com.clickhouse_jdbc-v2-0.8.0.jar
mkpipe_extractor_clickhouse/jars/com.fasterxml.jackson.core_jackson-core-2.17.2.jar
mkpipe_extractor_clickhouse/jars/commons-codec_commons-codec-1.17.1.jar
mkpipe_extractor_clickhouse/jars/commons-io_commons-io-2.16.1.jar
mkpipe_extractor_clickhouse/jars/org.apache.commons_commons-compress-1.27.1.jar
mkpipe_extractor_clickhouse/jars/org.apache.commons_commons-lang3-3.16.0.jar
mkpipe_extractor_clickhouse/jars/org.apache.httpcomponents.client5_httpclient5-5.2.1.jar
mkpipe_extractor_clickhouse/jars/org.apache.httpcomponents.core5_httpcore5-5.2.1.jar
mkpipe_extractor_clickhouse/jars/org.apache.httpcomponents.core5_httpcore5-h2-5.2.jar
mkpipe_extractor_clickhouse/jars/org.lz4_lz4-pure-java-1.8.0.jar
mkpipe_extractor_clickhouse/jars/org.ow2.asm_asm-9.5.jar
mkpipe_extractor_clickhouse/jars/org.roaringbitmap_RoaringBitmap-0.9.47.jar
mkpipe_extractor_clickhouse/jars/org.roaringbitmap_shims-0.9.47.jar
mkpipe_extractor_clickhouse/jars/org.slf4j_slf4j-api-2.0.7.jar
mkpipe_extractor_clickhouse-0.2.0.dist-info/licenses/LICENSE
mkpipe_extractor_clickhouse-0.2.0.dist-info/METADATA
mkpipe_extractor_clickhouse-0.2.0.dist-info/WHEEL
mkpipe_extractor_clickhouse-0.2.0.dist-info/entry_points.txt
mkpipe_extractor_clickhouse-0.2.0.dist-info/top_level.txt
mkpipe_extractor_clickhouse-0.2.0.dist-info/RECORD
